btc2fiat.py
btc2fiat-0.1.20.dist-info/METADATA
btc2fiat-0.1.20.dist-info/WHEEL
btc2fiat-0.1.20.dist-info/entry_points.txt
btc2fiat-0.1.20.dist-info/top_level.txt
btc2fiat-0.1.20.dist-info/RECORD
